common_patterns/__init__.py
common_patterns/common_patterns.py
common_patterns-2.0.1.dist-info/LICENSE
common_patterns-2.0.1.dist-info/METADATA
common_patterns-2.0.1.dist-info/WHEEL
common_patterns-2.0.1.dist-info/top_level.txt
common_patterns-2.0.1.dist-info/RECORD
